matrixbrain/LICENSE
matrixbrain/UNKNOWN.egg-info/PKG-INFO
matrixbrain/UNKNOWN.egg-info/SOURCES.txt
matrixbrain/UNKNOWN.egg-info/dependency_links.txt
matrixbrain/UNKNOWN.egg-info/top_level.txt
matrixbrain/__init__.py
matrixbrain/matrixbrain.py
matrixbrain-0.1.17.dist-info/entry_points.txt
matrixbrain-0.1.17.dist-info/WHEEL
matrixbrain-0.1.17.dist-info/METADATA
matrixbrain-0.1.17.dist-info/RECORD
