Metadata-Version: 2.1
Name: matrixbrain
Version: 0.1.17
Summary: Use machine learning to transform documents ( pdf, txt, doc ) in anki decks.
License: MIT
Author: Huggyturd
Author-email: cloura.dev@gmail.com
Requires-Python: >=3.8,<4.0
Classifier: License :: OSI Approved :: MIT License
Classifier: Programming Language :: Python :: 3
Classifier: Programming Language :: Python :: 3.10
Classifier: Programming Language :: Python :: 3.8
Classifier: Programming Language :: Python :: 3.9
Requires-Dist: farm-haystack (>=1.2.0,<2.0.0)
Requires-Dist: genanki (>=0.13.0,<0.14.0)
Requires-Dist: tqdm (>=4.63.0,<5.0.0)
